neuroflow/__init__.py
neuroflow/cli.py
neuroflow/atlases/__init__.py
neuroflow/atlases/atlases.py
neuroflow/atlases/utils.py
neuroflow/atlases/available_atlases/__init__.py
neuroflow/atlases/available_atlases/available_atlases.py
neuroflow/atlases/available_atlases/fan2016/references.bib
neuroflow/atlases/available_atlases/fan2016/MNI152/space-MNI152_atlas-fan2016_res-1mm_dseg.csv
neuroflow/atlases/available_atlases/fan2016/MNI152/space-MNI152_atlas-fan2016_res-1mm_dseg.nii.gz
neuroflow/atlases/available_atlases/fan2016/MNI152/space-MNI152_atlas-fan2016_res-1mm_dseg.tsv
neuroflow/atlases/available_atlases/fan2016/fsaverage/desc-lut_space-fsaverage_atlas-fan2016.txt
neuroflow/atlases/available_atlases/fan2016/fsaverage/hemi-L_space-fsaverage_atlas-fan2016.gcs
neuroflow/atlases/available_atlases/fan2016/fsaverage/hemi-R_space-fsaverage_atlas-fan2016.gcs
neuroflow/atlases/available_atlases/fan2016/fsaverage/hemi-subcortex_space-fsaverage_atlas-fan2016.gca
neuroflow/atlases/available_atlases/fan2016/fsaverage/fsaverage_164k/hemi-L_space-fsaverage_atlas-fan2016_den-164k.label.gii
neuroflow/atlases/available_atlases/fan2016/fsaverage/fsaverage_164k/hemi-R_space-fsaverage_atlas-fan2016_den-164k.label.gii
neuroflow/atlases/available_atlases/fan2016/fsaverage/fsaverage_164k/space-fsaverage_atlas-fan2016_den-164k.dlabel.nii
neuroflow/atlases/available_atlases/fan2016/fsaverage/fsaverage_32k/hemi-L_space-fsaverage_atlas-fan2016_den-32k.label.gii
neuroflow/atlases/available_atlases/fan2016/fsaverage/fsaverage_32k/hemi-R_space-fsaverage_atlas-fan2016_den-32k.label.gii
neuroflow/atlases/available_atlases/fan2016/fsaverage/fsaverage_32k/space-fsaverage_atlas-fan2016_den-32k.dlabel.nii
neuroflow/atlases/available_atlases/huang2022/references.bib
neuroflow/atlases/available_atlases/huang2022/MNI152/space-MNI152_atlas-huang2022_res-1mm_dseg.csv
neuroflow/atlases/available_atlases/huang2022/MNI152/space-MNI152_atlas-huang2022_res-1mm_dseg.nii.gz
neuroflow_yalab-0.1.9.dist-info/AUTHORS.rst
neuroflow_yalab-0.1.9.dist-info/LICENSE
neuroflow_yalab-0.1.9.dist-info/METADATA
neuroflow_yalab-0.1.9.dist-info/WHEEL
neuroflow_yalab-0.1.9.dist-info/entry_points.txt
neuroflow_yalab-0.1.9.dist-info/top_level.txt
neuroflow_yalab-0.1.9.dist-info/RECORD
