Metadata-Version: 2.2
Name: neuroflow-yalab
Version: 0.1.9
Summary: NeuroFlow: A streamlined toolkit for DWI post-processing, offering advanced analysis and visualization for neuroimaging research.
Author-email: Gal Kepler <galkepler@gmail.com>
Maintainer-email: Gal Kepler <galkepler@gmail.com>
License: MIT license
Project-URL: bugs, https://github.com/{{ cookiecutter.github_username }}/{{ cookiecutter.project_slug }}/issues
Project-URL: changelog, https://github.com/{{ cookiecutter.github_username }}/{{ cookiecutter.project_slug }}/blob/master/changelog.md
Project-URL: homepage, https://github.com/{{ cookiecutter.github_username }}/{{ cookiecutter.project_slug }}
Classifier: Development Status :: 3 - Alpha
Classifier: Intended Audience :: Developers
Classifier: License :: OSI Approved :: MIT License
Classifier: Programming Language :: Python :: 3
Classifier: Programming Language :: Python :: 3.9
Classifier: Programming Language :: Python :: 3.10
Classifier: Programming Language :: Python :: 3.11
License-File: LICENSE
License-File: AUTHORS.rst
Requires-Dist: typer
Requires-Dist: click
Requires-Dist: geopy~=2.4
Requires-Dist: gspread~=6.1
Requires-Dist: Jinja2~=3.1
Requires-Dist: meteostat~=1.6
Requires-Dist: nibabel~=5.2
Requires-Dist: nilearn~=0.10
Requires-Dist: nipype~=1.8
Requires-Dist: numpy~=1.26
Requires-Dist: oauth2client~=4.1
Requires-Dist: pandas~=2.2
Requires-Dist: scipy~=1.13
Requires-Dist: matplotlib~=3.8
Requires-Dist: dipy~=1.9
Requires-Dist: ipywidgets~=8.1
Requires-Dist: virtualenv~=20.25
Requires-Dist: tox~=4.14
Requires-Dist: black~=24.4
Requires-Dist: flake8~=7.0
Requires-Dist: isort~=5.13
Requires-Dist: ruff~=0.3
Requires-Dist: setuptools==69
Provides-Extra: dev
Requires-Dist: coverage; extra == "dev"
Requires-Dist: mypy; extra == "dev"
Requires-Dist: pytest; extra == "dev"
Requires-Dist: ruff; extra == "dev"
Requires-Dist: black; extra == "dev"
Requires-Dist: flake8; extra == "dev"
Requires-Dist: isort; extra == "dev"
Requires-Dist: tox; extra == "dev"
